mailengine/__init__.py
mailengine/client.py
mailengine/models.py
mailengine_sdk-0.1.0.dev0.dist-info/METADATA
mailengine_sdk-0.1.0.dev0.dist-info/WHEEL
mailengine_sdk-0.1.0.dev0.dist-info/top_level.txt
mailengine_sdk-0.1.0.dev0.dist-info/RECORD
