Metadata-Version: 2.1
Name: mailengine-sdk
Version: 0.1.0.dev0
Summary: Python SDK for MailEngine
Home-page: https://github.com/dominik-gralka/mailengine-sdk-py
Author: Umbratic
Author-email: contact@umbratic.com
Classifier: Programming Language :: Python :: 3
Classifier: License :: OSI Approved :: MIT License
Classifier: Operating System :: OS Independent
Requires-Dist: requests
